[{"clasa": "XI", "judet": "Constanta", "rank": "1", "id": "98c36d1b-586f-4d31-82f4-947caa8de8fb", "punctaj": "94.5201", "absent": false, "nume": "?"}, {"clasa": "X", "judet": "Constanta", "rank": "1", "id": "9a225f1b-f0d4-4e26-8cbd-6a0137e27225", "punctaj": "62.5642", "absent": false, "nume": "rm -r /life"}, {"clasa": "XI", "judet": "Constanta", "rank": "2", "id": "98a3cf56-f671-449e-a02a-00de9572d766", "punctaj": "61.3766", "absent": false, "nume": "viflaem2"}, {"clasa": "XI", "judet": "Constanta", "rank": "3", "id": "9b4745e1-6d0c-486f-8bc2-92807ed04ebe", "punctaj": "42.3718", "absent": false, "nume": "Dodu Andrei Daniel"}, {"clasa": "XII", "judet": "Constanta", "rank": "1", "id": "9b5814e9-7660-49bd-b7e4-9815349468f7", "punctaj": "40.4", "absent": false, "nume": "Capra Petru Valentin"}, {"clasa": "X", "judet": "Constanta", "rank": "2", "id": "9b5f8756-a523-4cb4-8439-942e3f1baaff", "punctaj": "33.9707", "absent": false, "nume": "Buzdugan Rare\u0219-Andrei"}, {"clasa": "XII", "judet": "Constanta", "rank": "2", "id": "9b5f3856-7360-405a-9808-75f35aef2b74", "punctaj": "24.7644", "absent": false, "nume": "Minzu Mihai"}, {"clasa": "XII", "judet": "Constanta", "rank": "3", "id": "9b6774f4-e2be-444a-a05f-1e2b4c5fac8d", "punctaj": "20.0529", "absent": false, "nume": "Alexandra Vlad"}]